CHANGES.txt
DEPENDENCES.txt
README.txt
TODO.txt
setup.py
src/ng/__init__.py
src/ng.app.objectqueue.egg-info/PKG-INFO
src/ng.app.objectqueue.egg-info/SOURCES.txt
src/ng.app.objectqueue.egg-info/dependency_links.txt
src/ng.app.objectqueue.egg-info/namespace_packages.txt
src/ng.app.objectqueue.egg-info/not-zip-safe
src/ng.app.objectqueue.egg-info/requires.txt
src/ng.app.objectqueue.egg-info/top_level.txt
src/ng/app/__init__.py
src/ng/app/objectqueue/__init__.py
src/ng/app/objectqueue/configure.zcml
src/ng/app/objectqueue/interfaces.py
src/ng/app/objectqueue/ng.app.objectqueue.txt
src/ng/app/objectqueue/objectqueue.py
src/ng/app/objectqueue/objectqueueannotationadapter.py
src/ng/app/objectqueue/objectqueueutilityadapter.py
src/ng/app/objectqueue/browser/__init__.py
src/ng/app/objectqueue/browser/configure.zcml
src/ng/app/objectqueue/demo/__init__.py
src/ng/app/objectqueue/demo/configure.zcml
src/ng/app/objectqueue/etc/ng.app.objectqueue-configure.zcml
src/ng/app/objectqueue/objectqueuehandle/__init__.py
src/ng/app/objectqueue/objectqueuehandle/configure.zcml
src/ng/app/objectqueue/objectqueuehandle/objectqueuealladapter.py
src/ng/app/objectqueue/objectqueuehandle/objectqueuehandler.py
src/ng/app/objectqueue/objectqueuehandle/objectqueuehandler.txt
src/ng/app/objectqueue/objectqueuehandle/objectqueueutilities.py
src/ng/app/objectqueue/queueutility/__init__.py
src/ng/app/objectqueue/queueutility/configure.zcml
src/ng/app/objectqueue/queueutility/queueutility.py