Metadata-Version: 1.0
Name: ng.app.objectqueue
Version: 0.0.8
Summary: Cached queue for object
Home-page: http://www.dreambot.ru/product/DreamBotZope3Releases/ng.app.objectqueue
Author: Yegor Shershnev
Author-email: dbdt@dreambot.ru
License: GPL v2.1
Platform: UNKNOWN
Classifier: Environment :: Web Environment
Classifier: Intended Audience :: Developers
Classifier: License :: OSI Approved :: GNU General Public License (GPL)
Classifier: Programming Language :: Python
Classifier: Operating System :: OS Independent
Classifier: Topic :: Internet :: WWW/HTTP
Classifier: Framework :: Zope3
